fluent_utils/__init__.py
fluent_utils/ajax.py
fluent_utils/load.py
fluent_utils/django_compat/__init__.py
fluent_utils/django_compat/fluent_compat.py
fluent_utils/dry/__init__.py
fluent_utils/dry/admin.py
fluent_utils/dry/fields.py
fluent_utils/softdeps/__init__.py
fluent_utils/softdeps/any_imagefield.py
fluent_utils/softdeps/any_urlfield.py
fluent_utils/softdeps/comments.py
fluent_utils/softdeps/fluent_pages.py
fluent_utils/softdeps/taggit.py
fluent_utils/tests/__init__.py
fluent_utils/tests/import_test.py
fluent_utils/tests/test_django_compat.py
fluent_utils/tests/test_dry.py
fluent_utils/tests/test_load.py
fluent_utils/tests/test_softdeps.py
django_fluent_utils-3.0.1.dist-info/AUTHORS
django_fluent_utils-3.0.1.dist-info/LICENSE
django_fluent_utils-3.0.1.dist-info/METADATA
django_fluent_utils-3.0.1.dist-info/WHEEL
django_fluent_utils-3.0.1.dist-info/top_level.txt
django_fluent_utils-3.0.1.dist-info/RECORD
